{
  "configVersion": 1,
  "timestamp": 1765899629741,
  "index": "/index.html",
  "assetGroups": [
    {
      "name": "app",
      "installMode": "prefetch",
      "updateMode": "prefetch",
      "cacheQueryOptions": {
        "ignoreVary": true
      },
      "urls": [
        "/chunk-25FGV4CB.js",
        "/chunk-25SRV6P6.js",
        "/chunk-2IHK6VWL.js",
        "/chunk-2J46Y3L2.js",
        "/chunk-2O7R4JDZ.js",
        "/chunk-2UUOIJQS.js",
        "/chunk-3VEW6XJI.js",
        "/chunk-46SQD22S.js",
        "/chunk-52OL5FSZ.js",
        "/chunk-5G224GAC.js",
        "/chunk-5HWXIJG3.js",
        "/chunk-5KUHHG2T.js",
        "/chunk-5PM6ZAKI.js",
        "/chunk-5REQRI7Z.js",
        "/chunk-63RWRTVN.js",
        "/chunk-6DJDMNPN.js",
        "/chunk-6J2M43DP.js",
        "/chunk-6JWNTJQL.js",
        "/chunk-6ZPJXFSI.js",
        "/chunk-77O6N62K.js",
        "/chunk-7AW62Q5F.js",
        "/chunk-7NJZLNB2.js",
        "/chunk-AGUNJJQQ.js",
        "/chunk-AVZ6QDVK.js",
        "/chunk-BUO67IH7.js",
        "/chunk-C6RC7WHE.js",
        "/chunk-CBVPYAD4.js",
        "/chunk-CCVWDFGZ.js",
        "/chunk-CTT3VBEL.js",
        "/chunk-DLRADPMP.js",
        "/chunk-EG2SEJRQ.js",
        "/chunk-EGBRRXRU.js",
        "/chunk-FKCVYBTO.js",
        "/chunk-FQUSSCGW.js",
        "/chunk-FZ6UKKBF.js",
        "/chunk-GB2LOC4P.js",
        "/chunk-GKTD2TDN.js",
        "/chunk-H5EASP7Q.js",
        "/chunk-H63IZK7M.js",
        "/chunk-HE5QBO3I.js",
        "/chunk-HSVTR3T3.js",
        "/chunk-IZCHANQD.js",
        "/chunk-JV2GB5RZ.js",
        "/chunk-K4ZJ7WWT.js",
        "/chunk-K5PQ55EU.js",
        "/chunk-K7KCRJWB.js",
        "/chunk-KO423GKH.js",
        "/chunk-KSWP2LJG.js",
        "/chunk-L74Q7YED.js",
        "/chunk-LFYIQ2BJ.js",
        "/chunk-LKEYYCPN.js",
        "/chunk-LL53MJEV.js",
        "/chunk-M42W3MMU.js",
        "/chunk-M4AJCJ7D.js",
        "/chunk-MHOEP35Z.js",
        "/chunk-ML2RJPCQ.js",
        "/chunk-MWPWTIW3.js",
        "/chunk-NQY4IIVY.js",
        "/chunk-OG6EM5RT.js",
        "/chunk-OHJW6RJF.js",
        "/chunk-ORLPO64Q.js",
        "/chunk-OZIEGSRX.js",
        "/chunk-P4XT6G44.js",
        "/chunk-PWSH4HYI.js",
        "/chunk-QLT6AE7C.js",
        "/chunk-QMPDHNFK.js",
        "/chunk-QUD2QF3N.js",
        "/chunk-R2RV5J47.js",
        "/chunk-R44HSUSI.js",
        "/chunk-R7DX4UKA.js",
        "/chunk-RBU5VOLW.js",
        "/chunk-RI34TUXH.js",
        "/chunk-RWZ5KVH3.js",
        "/chunk-SNWNQD3U.js",
        "/chunk-STTCBUMV.js",
        "/chunk-SVCBOY2C.js",
        "/chunk-TNTO7MDB.js",
        "/chunk-TR6HYK2P.js",
        "/chunk-TULW32F7.js",
        "/chunk-TW6KLVVD.js",
        "/chunk-UF24ZCGU.js",
        "/chunk-UX7NPTUT.js",
        "/chunk-VJPJWAJN.js",
        "/chunk-VLYNWEKA.js",
        "/chunk-VV2Q5YND.js",
        "/chunk-W3LWWWZE.js",
        "/chunk-W5TG2O2T.js",
        "/chunk-WA4IDKTA.js",
        "/chunk-WGVMEIUC.js",
        "/chunk-WMXPQ6KC.js",
        "/chunk-WN4O36XD.js",
        "/chunk-XNSY7GXF.js",
        "/chunk-YLIZRCFG.js",
        "/chunk-YR5O7N4M.js",
        "/chunk-ZEE7YWUE.js",
        "/chunk-ZLARDY7D.js",
        "/chunk-ZUD3KH72.js",
        "/chunk-ZXYJ7DLS.js",
        "/favicon.ico",
        "/index.html",
        "/main-LBLMGDGH.js",
        "/manifest.webmanifest",
        "/polyfills-5CFQRCPP.js",
        "/styles-INIAKHPG.css"
      ],
      "patterns": []
    },
    {
      "name": "assets",
      "installMode": "lazy",
      "updateMode": "prefetch",
      "cacheQueryOptions": {
        "ignoreVary": true
      },
      "urls": [
        "/assets/fonts/Manrope/Manrope-VariableFont_wght.ttf",
        "/assets/fonts/Manrope/static/Manrope-Bold.ttf",
        "/assets/fonts/Manrope/static/Manrope-ExtraBold.ttf",
        "/assets/fonts/Manrope/static/Manrope-ExtraLight.ttf",
        "/assets/fonts/Manrope/static/Manrope-Light.ttf",
        "/assets/fonts/Manrope/static/Manrope-Medium.ttf",
        "/assets/fonts/Manrope/static/Manrope-Regular.ttf",
        "/assets/fonts/Manrope/static/Manrope-SemiBold.ttf",
        "/assets/fonts/Roboto/Roboto-Italic-VariableFont_wdth,wght.ttf",
        "/assets/fonts/Roboto/Roboto-VariableFont_wdth,wght.ttf",
        "/assets/fonts/Roboto/static/Roboto-Black.ttf",
        "/assets/fonts/Roboto/static/Roboto-BlackItalic.ttf",
        "/assets/fonts/Roboto/static/Roboto-Bold.ttf",
        "/assets/fonts/Roboto/static/Roboto-BoldItalic.ttf",
        "/assets/fonts/Roboto/static/Roboto-ExtraBold.ttf",
        "/assets/fonts/Roboto/static/Roboto-ExtraBoldItalic.ttf",
        "/assets/fonts/Roboto/static/Roboto-ExtraLight.ttf",
        "/assets/fonts/Roboto/static/Roboto-ExtraLightItalic.ttf",
        "/assets/fonts/Roboto/static/Roboto-Italic.ttf",
        "/assets/fonts/Roboto/static/Roboto-Light.ttf",
        "/assets/fonts/Roboto/static/Roboto-LightItalic.ttf",
        "/assets/fonts/Roboto/static/Roboto-Medium.ttf",
        "/assets/fonts/Roboto/static/Roboto-MediumItalic.ttf",
        "/assets/fonts/Roboto/static/Roboto-Regular.ttf",
        "/assets/fonts/Roboto/static/Roboto-SemiBold.ttf",
        "/assets/fonts/Roboto/static/Roboto-SemiBoldItalic.ttf",
        "/assets/fonts/Roboto/static/Roboto-Thin.ttf",
        "/assets/fonts/Roboto/static/Roboto-ThinItalic.ttf",
        "/assets/fonts/Roboto/static/Roboto_Condensed-Black.ttf",
        "/assets/fonts/Roboto/static/Roboto_Condensed-BlackItalic.ttf",
        "/assets/fonts/Roboto/static/Roboto_Condensed-Bold.ttf",
        "/assets/fonts/Roboto/static/Roboto_Condensed-BoldItalic.ttf",
        "/assets/fonts/Roboto/static/Roboto_Condensed-ExtraBold.ttf",
        "/assets/fonts/Roboto/static/Roboto_Condensed-ExtraBoldItalic.ttf",
        "/assets/fonts/Roboto/static/Roboto_Condensed-ExtraLight.ttf",
        "/assets/fonts/Roboto/static/Roboto_Condensed-ExtraLightItalic.ttf",
        "/assets/fonts/Roboto/static/Roboto_Condensed-Italic.ttf",
        "/assets/fonts/Roboto/static/Roboto_Condensed-Light.ttf",
        "/assets/fonts/Roboto/static/Roboto_Condensed-LightItalic.ttf",
        "/assets/fonts/Roboto/static/Roboto_Condensed-Medium.ttf",
        "/assets/fonts/Roboto/static/Roboto_Condensed-MediumItalic.ttf",
        "/assets/fonts/Roboto/static/Roboto_Condensed-Regular.ttf",
        "/assets/fonts/Roboto/static/Roboto_Condensed-SemiBold.ttf",
        "/assets/fonts/Roboto/static/Roboto_Condensed-SemiBoldItalic.ttf",
        "/assets/fonts/Roboto/static/Roboto_Condensed-Thin.ttf",
        "/assets/fonts/Roboto/static/Roboto_Condensed-ThinItalic.ttf",
        "/assets/fonts/Roboto/static/Roboto_SemiCondensed-Black.ttf",
        "/assets/fonts/Roboto/static/Roboto_SemiCondensed-BlackItalic.ttf",
        "/assets/fonts/Roboto/static/Roboto_SemiCondensed-Bold.ttf",
        "/assets/fonts/Roboto/static/Roboto_SemiCondensed-BoldItalic.ttf",
        "/assets/fonts/Roboto/static/Roboto_SemiCondensed-ExtraBold.ttf",
        "/assets/fonts/Roboto/static/Roboto_SemiCondensed-ExtraBoldItalic.ttf",
        "/assets/fonts/Roboto/static/Roboto_SemiCondensed-ExtraLight.ttf",
        "/assets/fonts/Roboto/static/Roboto_SemiCondensed-ExtraLightItalic.ttf",
        "/assets/fonts/Roboto/static/Roboto_SemiCondensed-Italic.ttf",
        "/assets/fonts/Roboto/static/Roboto_SemiCondensed-Light.ttf",
        "/assets/fonts/Roboto/static/Roboto_SemiCondensed-LightItalic.ttf",
        "/assets/fonts/Roboto/static/Roboto_SemiCondensed-Medium.ttf",
        "/assets/fonts/Roboto/static/Roboto_SemiCondensed-MediumItalic.ttf",
        "/assets/fonts/Roboto/static/Roboto_SemiCondensed-Regular.ttf",
        "/assets/fonts/Roboto/static/Roboto_SemiCondensed-SemiBold.ttf",
        "/assets/fonts/Roboto/static/Roboto_SemiCondensed-SemiBoldItalic.ttf",
        "/assets/fonts/Roboto/static/Roboto_SemiCondensed-Thin.ttf",
        "/assets/fonts/Roboto/static/Roboto_SemiCondensed-ThinItalic.ttf",
        "/assets/icons/icon-192x192.png",
        "/assets/icons/icon-512x512.png",
        "/assets/images/benchmarks/serial_linear.svg",
        "/assets/images/benchmarks/serial_log.svg",
        "/assets/images/benchmarks/usb_linear.svg",
        "/assets/images/benchmarks/usb_log.svg",
        "/assets/images/branding/cteno_logo_dark.svg",
        "/assets/images/branding/cteno_logo_light.svg",
        "/assets/images/branding/logo_horizontal.png",
        "/assets/images/hardware/m5stack/1to3hub.webp",
        "/assets/images/hardware/m5stack/cable.webp",
        "/assets/images/hardware/m5stack/cardputer.webp",
        "/assets/images/hardware/m5stack/dac.webp",
        "/assets/images/hardware/m5stack/dual_button.webp",
        "/assets/images/hardware/m5stack/extend_io2.webp",
        "/assets/images/hardware/m5stack/flashlight.webp",
        "/assets/images/hardware/m5stack/hub1to6.webp",
        "/assets/images/hardware/m5stack/hub1to6_io.webp",
        "/assets/images/hardware/m5stack/joystick.webp",
        "/assets/images/hardware/m5stack/photo_resistance.webp",
        "/assets/images/hardware/units/dac.svg",
        "/assets/images/hardware/units/dual_button.svg",
        "/assets/images/hardware/units/ext_io.svg",
        "/assets/images/hardware/units/flashlight.svg",
        "/assets/images/hardware/units/joystick2.svg",
        "/assets/images/hardware/units/light_sensor.svg",
        "/assets/images/hardware/units/pahub.svg",
        "/assets/images/hardware/units/pbhub.svg",
        "/assets/images/hardware/units/units_diagram.svg",
        "/cteno_icon.svg",
        "/cteno_logo.svg",
        "/favicon.png",
        "/media/Manrope-VariableFont_wght-OKHRIJEM.ttf",
        "/media/Roboto-Italic-VariableFont_wdth,wght-JULNKXLA.ttf",
        "/media/Roboto-VariableFont_wdth,wght-TQJTUEE4.ttf"
      ],
      "patterns": []
    }
  ],
  "dataGroups": [],
  "hashTable": {
    "/assets/fonts/Manrope/Manrope-VariableFont_wght.ttf": "b190c931d200c0e72563c94a5f7568ca69bdb8b6",
    "/assets/fonts/Manrope/static/Manrope-Bold.ttf": "dbc0b874ad8b9f3415d0e9b4e22907890ca72327",
    "/assets/fonts/Manrope/static/Manrope-ExtraBold.ttf": "df131208d5c08ff782fbf12c264f473d8dacd83e",
    "/assets/fonts/Manrope/static/Manrope-ExtraLight.ttf": "bc714297659d8d6d987142c11987df3fe6f04b4e",
    "/assets/fonts/Manrope/static/Manrope-Light.ttf": "27d7897032dc0615ace6c53fd292107ae53280e5",
    "/assets/fonts/Manrope/static/Manrope-Medium.ttf": "b5e2c6265e0919163142bb8eac9b6450fb91f920",
    "/assets/fonts/Manrope/static/Manrope-Regular.ttf": "3f36e4904a42d23273ac346047c1b6bcf067ccfc",
    "/assets/fonts/Manrope/static/Manrope-SemiBold.ttf": "f7a023cd6c102b2ffa8bf729579552445970d62d",
    "/assets/fonts/Roboto/Roboto-Italic-VariableFont_wdth,wght.ttf": "eb51d6042f676b736a552744a77dc352d92a08e1",
    "/assets/fonts/Roboto/Roboto-VariableFont_wdth,wght.ttf": "6bd9646ab22c0301ce3adbfe8707213a67900404",
    "/assets/fonts/Roboto/static/Roboto-Black.ttf": "d1678489a8d5645f16486ec52d77b651ff0bf327",
    "/assets/fonts/Roboto/static/Roboto-BlackItalic.ttf": "d1e14166c8226143eea1730d92f518cc47d03462",
    "/assets/fonts/Roboto/static/Roboto-Bold.ttf": "508c35dee818addce6cc6d1fb6e42f039da5a7cf",
    "/assets/fonts/Roboto/static/Roboto-BoldItalic.ttf": "03440bfa71172aaa6b8ba6da86ac60d667b55c1e",
    "/assets/fonts/Roboto/static/Roboto-ExtraBold.ttf": "3dbfd71b6fbcfbd8e7ee8a8dd033dc5aaad63249",
    "/assets/fonts/Roboto/static/Roboto-ExtraBoldItalic.ttf": "0c1a0709d9772d20419c1b5868d19631c63861f6",
    "/assets/fonts/Roboto/static/Roboto-ExtraLight.ttf": "df556e64732e5c272349e13cb5f87591a1ae779b",
    "/assets/fonts/Roboto/static/Roboto-ExtraLightItalic.ttf": "1b0b602c97a479fed89900c64a0b9242d459ed19",
    "/assets/fonts/Roboto/static/Roboto-Italic.ttf": "55534e771bbbb6b649746802cabfdeb922b9eb3a",
    "/assets/fonts/Roboto/static/Roboto-Light.ttf": "318b44c0a32848f78bf11d4fbf3355d00647a796",
    "/assets/fonts/Roboto/static/Roboto-LightItalic.ttf": "565cd54ab54fdfa1be7c62fce75048d7ef0737e6",
    "/assets/fonts/Roboto/static/Roboto-Medium.ttf": "fa5192203f85ddb667579e1bdf26f12098bb873b",
    "/assets/fonts/Roboto/static/Roboto-MediumItalic.ttf": "debc1546314dd5655403df6965878d3f8dc41897",
    "/assets/fonts/Roboto/static/Roboto-Regular.ttf": "3bff51436aa7eb995d84cfc592cc63e1316bb400",
    "/assets/fonts/Roboto/static/Roboto-SemiBold.ttf": "9ca139684fe902c8310dd82991648376ac9838db",
    "/assets/fonts/Roboto/static/Roboto-SemiBoldItalic.ttf": "21a14c8c35225cbd714af050086d3b17a1ae5df8",
    "/assets/fonts/Roboto/static/Roboto-Thin.ttf": "8e098a207d2ace83e873d02b76acba903d819f74",
    "/assets/fonts/Roboto/static/Roboto-ThinItalic.ttf": "b20989b4dd1168286dca1f24193fe78f51e60f6b",
    "/assets/fonts/Roboto/static/Roboto_Condensed-Black.ttf": "317f765e1f770c422243ccdd7d0b8cf408c58db4",
    "/assets/fonts/Roboto/static/Roboto_Condensed-BlackItalic.ttf": "c367cbc303fe3adeaad06573145ece206edca674",
    "/assets/fonts/Roboto/static/Roboto_Condensed-Bold.ttf": "b872ba48fedf30d87dd5353b5e4b58285aef964b",
    "/assets/fonts/Roboto/static/Roboto_Condensed-BoldItalic.ttf": "3863e2d95d95e8bebeb15d0519fcf5a65bb35f89",
    "/assets/fonts/Roboto/static/Roboto_Condensed-ExtraBold.ttf": "e409e2cdf444475cafdb76c5ae26721e96483553",
    "/assets/fonts/Roboto/static/Roboto_Condensed-ExtraBoldItalic.ttf": "95500c4ad3305d0843fcce607e0748491f6b74f1",
    "/assets/fonts/Roboto/static/Roboto_Condensed-ExtraLight.ttf": "1cc9dfa74b6f7f11dc088c87b552db211cc3db5a",
    "/assets/fonts/Roboto/static/Roboto_Condensed-ExtraLightItalic.ttf": "cdb48490a752e60e2b15da5be3aec5cd061bdacd",
    "/assets/fonts/Roboto/static/Roboto_Condensed-Italic.ttf": "24b1d43d5a9474855065b0386695797ebca6d1bc",
    "/assets/fonts/Roboto/static/Roboto_Condensed-Light.ttf": "1daf12253cbd45c84a4f3b04d2ccea83d40446cb",
    "/assets/fonts/Roboto/static/Roboto_Condensed-LightItalic.ttf": "5c9b814f3127d42fdc32de6ee147bf044cd00565",
    "/assets/fonts/Roboto/static/Roboto_Condensed-Medium.ttf": "6e28f96625b03352e78420c2971aafa972178e4a",
    "/assets/fonts/Roboto/static/Roboto_Condensed-MediumItalic.ttf": "a4841c5d941a921e5a9947b8d5796b090287239f",
    "/assets/fonts/Roboto/static/Roboto_Condensed-Regular.ttf": "8870afc8d2c6f82cd46dac833e8dc644bf6d771e",
    "/assets/fonts/Roboto/static/Roboto_Condensed-SemiBold.ttf": "d42a31da6b171049086ebf69625e842d0029c8cd",
    "/assets/fonts/Roboto/static/Roboto_Condensed-SemiBoldItalic.ttf": "7d0e59b4d6454f7169972e4185aba192090a4eea",
    "/assets/fonts/Roboto/static/Roboto_Condensed-Thin.ttf": "f9726bc1c50d46bbde3465a5f122d083a157c512",
    "/assets/fonts/Roboto/static/Roboto_Condensed-ThinItalic.ttf": "08b7c9fbe3e6ecc218deac36bf85dc3d1eca75f5",
    "/assets/fonts/Roboto/static/Roboto_SemiCondensed-Black.ttf": "082786ff6c5447dd71d84cd958ad49550e34e946",
    "/assets/fonts/Roboto/static/Roboto_SemiCondensed-BlackItalic.ttf": "f8d806e89e03117842acf9201cb075d2462aa882",
    "/assets/fonts/Roboto/static/Roboto_SemiCondensed-Bold.ttf": "99fb3094f90c81f8e7170465a323c45cf4cf7228",
    "/assets/fonts/Roboto/static/Roboto_SemiCondensed-BoldItalic.ttf": "cbe1d896343a6af4d977064955c6aea762bceed2",
    "/assets/fonts/Roboto/static/Roboto_SemiCondensed-ExtraBold.ttf": "2f5bfa180dc855c534dc3b81a0b2b83738258c90",
    "/assets/fonts/Roboto/static/Roboto_SemiCondensed-ExtraBoldItalic.ttf": "d48131390678773688a10df726b97738143762fc",
    "/assets/fonts/Roboto/static/Roboto_SemiCondensed-ExtraLight.ttf": "b6acaaf04d5f10f75675165ff29f11abdc18d924",
    "/assets/fonts/Roboto/static/Roboto_SemiCondensed-ExtraLightItalic.ttf": "807eaf704c7520261e58de03470f22f7e637e8f3",
    "/assets/fonts/Roboto/static/Roboto_SemiCondensed-Italic.ttf": "9e565a7a8c94822df9ca33458f1ce1b97bd8d4b0",
    "/assets/fonts/Roboto/static/Roboto_SemiCondensed-Light.ttf": "d93dc296870245c2226379caba0f56a9edfbff06",
    "/assets/fonts/Roboto/static/Roboto_SemiCondensed-LightItalic.ttf": "069cfd565ba9a8ca8fa8bab6b3aaee1bf36ce9c8",
    "/assets/fonts/Roboto/static/Roboto_SemiCondensed-Medium.ttf": "140d18a97327a31fa332b0a22a907cfccc809b25",
    "/assets/fonts/Roboto/static/Roboto_SemiCondensed-MediumItalic.ttf": "ae767cd287317a77aabdb524dd556a0460d14888",
    "/assets/fonts/Roboto/static/Roboto_SemiCondensed-Regular.ttf": "3b088ea557c90e6dbf60894e06ef934ede330106",
    "/assets/fonts/Roboto/static/Roboto_SemiCondensed-SemiBold.ttf": "edc6d5cc92d79e84637a78cde2e3adfe4e085c2d",
    "/assets/fonts/Roboto/static/Roboto_SemiCondensed-SemiBoldItalic.ttf": "ba86508b1d08f6e0e4ff2ca71b35521007ed9994",
    "/assets/fonts/Roboto/static/Roboto_SemiCondensed-Thin.ttf": "efa3716adfba5bdb3ec38de4261c10c3c614ed51",
    "/assets/fonts/Roboto/static/Roboto_SemiCondensed-ThinItalic.ttf": "4015948dfdcc05da6c01e8950dc1f09bb0cc3ed0",
    "/assets/icons/icon-192x192.png": "377a13f8d334f5fd453bc32a37a085ecef0b38fb",
    "/assets/icons/icon-512x512.png": "2c126b65504447babb9b3206afc36ab3f4069d04",
    "/assets/images/benchmarks/serial_linear.svg": "00553935d8514427f2e887f359e25c2dbf57739c",
    "/assets/images/benchmarks/serial_log.svg": "3c6ead89fa8f3cac79e8238d2d12203d556dba35",
    "/assets/images/benchmarks/usb_linear.svg": "9a82981ba24e66ed12c8f62e6f4f39038b7e5ff6",
    "/assets/images/benchmarks/usb_log.svg": "6478db4fbdb52c7b6585a5e6bcca6ba04cc51c89",
    "/assets/images/branding/cteno_logo_dark.svg": "38eb0af8d62a39b06f10bfab96b564e4375cb8a9",
    "/assets/images/branding/cteno_logo_light.svg": "d987acd38493d2a8c72b98b07ee51c62ea56f972",
    "/assets/images/branding/logo_horizontal.png": "e4bd09a15cdfc18c09c6baa314c3f8ede7927678",
    "/assets/images/hardware/m5stack/1to3hub.webp": "02b2621fe728350278e09bb9a54cbdba8429050c",
    "/assets/images/hardware/m5stack/cable.webp": "bfa60895c8b6d1589c8c01c648a91db7efab5186",
    "/assets/images/hardware/m5stack/cardputer.webp": "f7d1dd969d51af1a44b7693d43933f5406883279",
    "/assets/images/hardware/m5stack/dac.webp": "1c037723f7d41a834fa45f879894436de830e075",
    "/assets/images/hardware/m5stack/dual_button.webp": "ece1497f9740a18dc93b34e2662c0f0b457ff784",
    "/assets/images/hardware/m5stack/extend_io2.webp": "f35e739dfe5f7b0c8ada7c433528886bb7dc291f",
    "/assets/images/hardware/m5stack/flashlight.webp": "25ab4b66eda05db8ef295b47b946a3b69bfe946c",
    "/assets/images/hardware/m5stack/hub1to6.webp": "d0492ec72b709a863ceedd61b1dabafe86edf34f",
    "/assets/images/hardware/m5stack/hub1to6_io.webp": "efa935e8659eabbd622967f86096167733b89b2d",
    "/assets/images/hardware/m5stack/joystick.webp": "a2c0de19361e1be99abe18a9a1ff05e054c65eb1",
    "/assets/images/hardware/m5stack/photo_resistance.webp": "a83d6046eba73e1e5992fbe7c6bf8fdbf345de17",
    "/assets/images/hardware/units/dac.svg": "c62650bcb9f1a32f6db4d0863dcbe6690d504ca7",
    "/assets/images/hardware/units/dual_button.svg": "068d2dbdc1b46a411e40b4e6775726e6ab99c70c",
    "/assets/images/hardware/units/ext_io.svg": "388bab708f1bf3f202a1e1364418d6df77a99cc7",
    "/assets/images/hardware/units/flashlight.svg": "762bd9841b26f260e97bbab9fabcd1a9886c1cff",
    "/assets/images/hardware/units/joystick2.svg": "876209520f9caeeb2ddb3f09f7e49f82c3d28617",
    "/assets/images/hardware/units/light_sensor.svg": "a6b8b7a69eca6e0695bc4eb06096420328bcd346",
    "/assets/images/hardware/units/pahub.svg": "a8e1b4c6a03ed8ed3cc08fc38617cb9023f7d145",
    "/assets/images/hardware/units/pbhub.svg": "b83ee699179260c9f0e218af66c7e1b545abeb4e",
    "/assets/images/hardware/units/units_diagram.svg": "5d35aff699e020ebfe6cc148d21bbc2781bc940c",
    "/chunk-25FGV4CB.js": "66df852d71fe2319cdf74ea73ceb253d61fd1813",
    "/chunk-25SRV6P6.js": "13b54283933c02f87596d43bd43622925d2c9ca4",
    "/chunk-2IHK6VWL.js": "d3d381210c71184fb0116a0440325293e0533a31",
    "/chunk-2J46Y3L2.js": "593ff1501341e6a5c30893e7ad8d8554b5433a67",
    "/chunk-2O7R4JDZ.js": "3df88e93b02a582816b93d78b9e248009148ae8f",
    "/chunk-2UUOIJQS.js": "399eaad020a46a8b557af13c0d0f0523a2818324",
    "/chunk-3VEW6XJI.js": "b45ccabec9a019be19f277fe55b63cbd6e000b44",
    "/chunk-46SQD22S.js": "5770384f49d3c52619125b9beeaab985dbdfd238",
    "/chunk-52OL5FSZ.js": "22d30be74e0c273797a5cefa0510a877d7054fd2",
    "/chunk-5G224GAC.js": "c695154b000c62574ed8816835cc3a8a7c7d02ea",
    "/chunk-5HWXIJG3.js": "85520429d412bc70b82ad4f6be5077c1ba477324",
    "/chunk-5KUHHG2T.js": "e4f3e0416234248f3a80d0737037450bdf7ac487",
    "/chunk-5PM6ZAKI.js": "be255299eac4e33496a34e4bc75131592f042daf",
    "/chunk-5REQRI7Z.js": "bc4acc6ad5883f3ed1fdb5af0101a2cadbccfd02",
    "/chunk-63RWRTVN.js": "d5e2b18a0231310ffe5854bbfebba7db713e672f",
    "/chunk-6DJDMNPN.js": "8d61abbd38dc70733f4b78e6aad02b978b57e3ff",
    "/chunk-6J2M43DP.js": "762e94a3d3c3e259b703a0d012c05ed854f40c12",
    "/chunk-6JWNTJQL.js": "6fff91be25860b5959b291f04099649e1feee8c4",
    "/chunk-6ZPJXFSI.js": "cca5b5054d5c1da7cd57c61606e0ed64b4aac75d",
    "/chunk-77O6N62K.js": "66572ca917005c0f952fe2431051945dd475afb0",
    "/chunk-7AW62Q5F.js": "e71a986470262d5360e29a7f21b925e6dc2033f2",
    "/chunk-7NJZLNB2.js": "8a5a60d2d2d59069b5b070a5148264bd9301897a",
    "/chunk-AGUNJJQQ.js": "006fdf674dae949c9d8196911203adfd02857b95",
    "/chunk-AVZ6QDVK.js": "590c80ac1fafbe4df308ede36403b22ef775291e",
    "/chunk-BUO67IH7.js": "091fa9972f0bb30f28cd814c9568c6c0eaa8c8cf",
    "/chunk-C6RC7WHE.js": "c804ce18534acb1057713eef4fabe2dc6dad7e94",
    "/chunk-CBVPYAD4.js": "ad3f49886f11d34e233cfe876278234f42700cec",
    "/chunk-CCVWDFGZ.js": "e04c4f92ce8b7301c4fc338e0e0a4896c9d179ed",
    "/chunk-CTT3VBEL.js": "1e01f59a86300369e7a601a243311a2b7575431f",
    "/chunk-DLRADPMP.js": "e3aae1cda95b26ad3c78bdf7e1ea117e24492093",
    "/chunk-EG2SEJRQ.js": "b584d84db359329ea3e3daeb65c36c6e299eaf11",
    "/chunk-EGBRRXRU.js": "b3d9e8a4aa32950021e7f03c39f6aa951212b795",
    "/chunk-FKCVYBTO.js": "926c4c5bf5e292d4238dd5bddda7ca8dda64c9bf",
    "/chunk-FQUSSCGW.js": "0f795e240519050587b45ecd240a343373b63ad5",
    "/chunk-FZ6UKKBF.js": "5a5f9e71c54a9abd674f1def0e7bdf05caa78ab7",
    "/chunk-GB2LOC4P.js": "bbc5be6fe05d007c98171c99235008f51e54bd3f",
    "/chunk-GKTD2TDN.js": "df8b857f7459a719f128b94993ded21dcb026242",
    "/chunk-H5EASP7Q.js": "ee07b25003c3f01377ffff87b7cef71526b57bf7",
    "/chunk-H63IZK7M.js": "e3b50e7d4528a955c8959abf76653112cb98e65f",
    "/chunk-HE5QBO3I.js": "cb796de4ad7b91f1ef9d89e4eec43205bea320fd",
    "/chunk-HSVTR3T3.js": "8df38e40ccddf7a2c47083eda0744309af9caf68",
    "/chunk-IZCHANQD.js": "13871b4d38e9ccf886352da05340d6653935a9b4",
    "/chunk-JV2GB5RZ.js": "b1143f4bb549181478dc8ef21c85d96a0e837488",
    "/chunk-K4ZJ7WWT.js": "a2b6d5d88a34629119ce6b122316843c16c62e8c",
    "/chunk-K5PQ55EU.js": "4551ee7f33d61c47767038eccbd76bf8a0c4a8e0",
    "/chunk-K7KCRJWB.js": "7a9f0d1c3a2fb7731bd09e8dedf0922a715a3532",
    "/chunk-KO423GKH.js": "1342ab26c0e7bce5d198f6a307f6b2afd624729a",
    "/chunk-KSWP2LJG.js": "0428aa7f46acc03832a69af04d3e19b6e6a6df73",
    "/chunk-L74Q7YED.js": "dcd0382ed05125a5c8fe6f3bbaa87f49ac55171b",
    "/chunk-LFYIQ2BJ.js": "b223c9a8cebc3456caa0536ac49b8efed64b3b70",
    "/chunk-LKEYYCPN.js": "7b05963634cb0a9e6c3f347857f3de244ab3b198",
    "/chunk-LL53MJEV.js": "19cf25d12c757216b92749cf4eb485100f364d30",
    "/chunk-M42W3MMU.js": "0e706e97d97f986203af933e8f369a14bda1605b",
    "/chunk-M4AJCJ7D.js": "0490e9cd91d99521c1735bc82d30ddd84d09c9bd",
    "/chunk-MHOEP35Z.js": "193f441b9e848c9919673f6d10d54b476bf07415",
    "/chunk-ML2RJPCQ.js": "e9180cf221ba3d69ec02a613a02302f5ab276fe7",
    "/chunk-MWPWTIW3.js": "a5db30ca063f1a0c9f68d44374fdda6403fb6279",
    "/chunk-NQY4IIVY.js": "27feb85f1c4a86716871f4b2a69033260c4b1878",
    "/chunk-OG6EM5RT.js": "e9f8793d4e65df8a9f8e57e55dd9b1313015d295",
    "/chunk-OHJW6RJF.js": "94a757c25c033fd032736e09a31c384169bc26ec",
    "/chunk-ORLPO64Q.js": "e55350b853a95f68c35161de5bf911f4a4b2ccfa",
    "/chunk-OZIEGSRX.js": "971b2ca4b153c531d317df25eacaa7386f76057d",
    "/chunk-P4XT6G44.js": "96d9ad2992bdc0d55ae9550ae3b73c060236298f",
    "/chunk-PWSH4HYI.js": "707accbeb6185b6036442d8e11421c741c4730fc",
    "/chunk-QLT6AE7C.js": "7d34c4daa4b2ce35be7b9fad9275fa538250bc12",
    "/chunk-QMPDHNFK.js": "e70e60c17628ac4b3ec10e5513619865cdb8752b",
    "/chunk-QUD2QF3N.js": "a4ba45d70378089ba677b19e573c2ac6a3f166fb",
    "/chunk-R2RV5J47.js": "2176debc8ad8fb9a843fd0ea788e53770e7103eb",
    "/chunk-R44HSUSI.js": "5ae81c548ffecf33c85120f0bbf2c1d50cef39ce",
    "/chunk-R7DX4UKA.js": "efd997244607c4837535055fff8289dab5929c35",
    "/chunk-RBU5VOLW.js": "bb8a4e2bcbd52fcc1b5f7dc2e12b2047f0158b6a",
    "/chunk-RI34TUXH.js": "db01edc6416fda9cf4e07c616cc6c2780b37cbad",
    "/chunk-RWZ5KVH3.js": "e95e2351ee787e6454531ca06e40f4d8f26bca08",
    "/chunk-SNWNQD3U.js": "05c836afc4d5f4908b368b23a5f001dadd8beae5",
    "/chunk-STTCBUMV.js": "0e8799220e0b1c2b96983651891e75522e5ea188",
    "/chunk-SVCBOY2C.js": "dc1f2bf14cc1061eeaef5c16c942f2eceab72c3e",
    "/chunk-TNTO7MDB.js": "b3736fd448ba839e651defefd340a435d08e9100",
    "/chunk-TR6HYK2P.js": "9b2049c83e7b20cab13591037aa6566e688392e8",
    "/chunk-TULW32F7.js": "8d8c472b38b37ca7d063a164d93dbd5d68aefcd1",
    "/chunk-TW6KLVVD.js": "9740703052da0444bdfa884e31dfcf646b5a0176",
    "/chunk-UF24ZCGU.js": "0c5018acc777616e5f0c0270960dadfa8351d2ea",
    "/chunk-UX7NPTUT.js": "a4e0555a06b8ce0e8947dc4c511e003e88cb2111",
    "/chunk-VJPJWAJN.js": "dc4a38514687f072d6cb973f8faaafaea269d9f2",
    "/chunk-VLYNWEKA.js": "712c82c2570d0844f90e719b293ecf3239e99f78",
    "/chunk-VV2Q5YND.js": "3e4d678d6fc96ce304a1b7f3dfbe47fe2695e5e1",
    "/chunk-W3LWWWZE.js": "cf2be32fddfbec67161313b974fe5024d48e0a21",
    "/chunk-W5TG2O2T.js": "690d9708335e0f8358fd3bc77fa414e72b24c5f3",
    "/chunk-WA4IDKTA.js": "f8ca460bf6ac163055f95e693019c8682759871c",
    "/chunk-WGVMEIUC.js": "98c857a0147927b30cf8f139fb576e7eff82e700",
    "/chunk-WMXPQ6KC.js": "1c330225bb18d9e7118a7951f4d83fd731b9c191",
    "/chunk-WN4O36XD.js": "8083d08404b398028ee20573c0c259a7b4d61a41",
    "/chunk-XNSY7GXF.js": "d6de5794c55b26436f8d3f9cf7620cc94f5d5913",
    "/chunk-YLIZRCFG.js": "08b5f97f88e35161918b4e704e75bf51447120f7",
    "/chunk-YR5O7N4M.js": "4a8f93e74cf6489de51fb754213e04d7168df29f",
    "/chunk-ZEE7YWUE.js": "1c44ab2146f417665573efa1ad4dd0399b8e635f",
    "/chunk-ZLARDY7D.js": "620a2335e32f87d960fc784445262b6b57900720",
    "/chunk-ZUD3KH72.js": "29db22a6ec5a4e67a4e255afdd0d8d84caf79411",
    "/chunk-ZXYJ7DLS.js": "f38554a918e9040462ae57b15b47cd9a3fdeb9d4",
    "/cteno_icon.svg": "fad385ff2973732222f4097e0bf4caf289a614a9",
    "/cteno_logo.svg": "564b5f13973c28b6eac245521065c0946d72cc78",
    "/favicon.ico": "28223e1554ef54327e9cbb5db015deafdfbcc944",
    "/favicon.png": "baef56891b99254e592dfab6a93f6d105dde4e1e",
    "/index.html": "29eb80139e67642cf36833f38fad927568d491d9",
    "/main-LBLMGDGH.js": "f2bcfb2848bb30baa2b3f5d3818a466a0139c290",
    "/manifest.webmanifest": "de015c3ef11c0fb334a652d6440fb0c5b3286325",
    "/media/Manrope-VariableFont_wght-OKHRIJEM.ttf": "b190c931d200c0e72563c94a5f7568ca69bdb8b6",
    "/media/Roboto-Italic-VariableFont_wdth,wght-JULNKXLA.ttf": "eb51d6042f676b736a552744a77dc352d92a08e1",
    "/media/Roboto-VariableFont_wdth,wght-TQJTUEE4.ttf": "6bd9646ab22c0301ce3adbfe8707213a67900404",
    "/polyfills-5CFQRCPP.js": "f2241e9a25858f895ce299d15f6f22e849e2fd72",
    "/styles-INIAKHPG.css": "f111672d596e14194ff19941a07b44f1011bac19"
  },
  "navigationUrls": [
    {
      "positive": true,
      "regex": "^\\/.*$"
    },
    {
      "positive": false,
      "regex": "^\\/(?:.+\\/)?[^/]*\\.[^/]*$"
    },
    {
      "positive": false,
      "regex": "^\\/(?:.+\\/)?[^/]*__[^/]*$"
    },
    {
      "positive": false,
      "regex": "^\\/(?:.+\\/)?[^/]*__[^/]*\\/.*$"
    }
  ],
  "navigationRequestStrategy": "performance"
}